{
  "432393745749639169": {
    "user_id": 432393745749639169,
    "age": "21",
    "gender": "남",
    "path": "예은",
    "nickname": "김무타",
    "timestamp": "2025-06-28T22:26:32.333082"
  },
  "697820001876312064": {
    "user_id": 697820001876312064,
    "age": "05",
    "gender": "남",
    "path": "1",
    "nickname": "2323",
    "timestamp": "2025-06-12T20:18:05.744477"
  },
  "875014610565099520": {
    "user_id": 875014610565099520,
    "age": "20",
    "gender": "여",
    "path": "무타",
    "nickname": "담이",
    "timestamp": "2025-06-14T14:47:18.803290"
  }
}